{"fields":[{"id":"a","label":"Type","type":"string"},{"id":"b","label":"Vehicles Category","type":"string"},{"id":"c","label":"Type of Vehicles","type":"string"},{"id":"d","label":"Newly registered - 2002-03","type":"string"},{"id":"e","label":"Newly registered - 2003-04","type":"string"},{"id":"f","label":"Total registered as on - 31.3.2003","type":"string"},{"id":"g","label":"Total registered as on - 31.3.2004","type":"string"}],"data":[["Transport","I. Multiaxled \/ Articulated Vehicles","Multiaxled \/ Articulated Vehicles","NA","2396","NA","4618"],["Transport","II. Trucks & Lorries","Trucks & Lorries","10576","15807","228198","238495"],["Transport","III. Light Motor Vehicles (Goods)","Four Wheelers","9696","15716","138138","149912"],["Transport","III. Light Motor Vehicles (Goods)","Three Wheelers","13585","19369","90019","106170"],["Transport","Total-III. Light Motor Vehicles (Goods)","Total Light Motor Vehicles (Goods)","23281","35085","228157","256082"],["Transport","IV. Buses","Stage carriages","989","1601","26991","27576"],["Transport","IV. Buses","Contract carriages","906","1625","12355","12904"],["Transport","IV. Buses","Private service vehicles","452","760","5997","6361"],["Transport","IV. Buses","Other buses","102","318","2008","2251"],["Transport","Total-IV. Buses","Total Buses","2449","4304","47351","49092"],["Transport","V. Taxis","Motor cabs","NA","NA","NA","NA"],["Transport","V. Taxis","Maxi cabs","NA","NA","NA","NA"],["Transport","V. Taxis","Other taxis","NA","NA","NA","NA"],["Transport","Total- V. Taxis","Total Taxis","8537","8165","94920","102475"],["Transport","VI. Light Motor Vehicles (Passengers)","Three seaters","NA","NA","NA","NA"],["Transport","VI. Light Motor Vehicles (Passengers)","Four to six seaters","NA","NA","NA","NA"],["Transport","Total- VI. Light Motor Vehicles (Passengers)","Total Light Motor Vehicles (Passengers)","43937","42034","463550","493142"],["Transport","VII. Motor cycles on hire","Motor cycles on hire","NA","NA","NA","NA"],["Transport","Total Transport(I to VII)","Total Transport","88780","107791","1062176","1143904"],["Non Transport","I. Two wheelers","Scooters","55135","65436","1497876","1562751"],["Non Transport","I. Two wheelers","Mopeds","60368","58811","1101358","1160864"],["Non Transport","I. Two wheelers","Motor cycles","447834","506154","2988428","3493179"],["Non Transport","Total-I. Two wheelers","Total Two wheelers","563337","630401","5587662","6216794"],["Non Transport","II. Cars","Cars","79258","101400","831261","924006"],["Non Transport","III. Jeeps","Jeeps","14677","18950","244025","262741"],["Non Transport","IV. Omni buses","Omni buses","44","60","12599","12609"],["Non Transport","V. Tractors","Tractors","8149","7579","194902","201940"],["Non Transport","VI. Trailers","Trailers","6493","4990","186100","190628"],["Non Transport","VII. Other vehicles not covered","Other vehicles not covered","786","893","15112","16111"],["Non Transport","Total Non Transport (I to VII)","Total Non-Transport","672744","764273","7071661","7824829"]]}