{"fields":[{"id":"a","label":"Type","type":"string"},{"id":"b","label":"Vehicles Category","type":"string"},{"id":"c","label":"Type of Vehicles","type":"string"},{"id":"d","label":"Newly registered - 2002-03","type":"string"},{"id":"e","label":"Newly registered - 2003-04","type":"string"},{"id":"f","label":"Total registered as on - 31.3.2003","type":"string"},{"id":"g","label":"Total registered as on - 31.3.2004","type":"string"}],"data":[["Transport","I. Multiaxled \/ Articulated Vehicles","Multiaxled \/ Articulated Vehicles","120","359","911","1270"],["Transport","II. Trucks & Lorries","Trucks & Lorries","2967","3269","35874","39143"],["Transport","III. Light Motor Vehicles (Goods)","Four Wheelers","609","1205","10247","11452"],["Transport","III. Light Motor Vehicles (Goods)","Three Wheelers","412","755","4479","5234"],["Transport","Total-III. Light Motor Vehicles (Goods)","Total Light Motor Vehicles (Goods)","1021","1960","14726","16686"],["Transport","IV. Buses","Stage carriages","NA","NA","NA","NA"],["Transport","IV. Buses","Contract carriages","NA","NA","NA","NA"],["Transport","IV. Buses","Private service vehicles","NA","NA","NA","NA"],["Transport","IV. Buses","Other buses","NA","NA","NA","NA"],["Transport","Total-IV. Buses","Total Buses","74","143","1900","2043"],["Transport","V. Taxis","Motor cabs","1205","412","4013","4425"],["Transport","V. Taxis","Maxi cabs","1659","2385","13377","15762"],["Transport","V. Taxis","Other taxis","150","229","1589","1818"],["Transport","Total- V. Taxis","Total Taxis","3014","3026","18979","22005"],["Transport","VI. Light Motor Vehicles (Passengers)","Three seaters","480","480","4811","5291"],["Transport","VI. Light Motor Vehicles (Passengers)","Four to six seaters","379","401","1782","2183"],["Transport","Total- VI. Light Motor Vehicles (Passengers)","Total Light Motor Vehicles (Passengers)","859","881","6593","7474"],["Transport","VII. Motor cycles on hire","Motor cycles on hire","NA","NA","NA","NA"],["Transport","Total Transport(I to VII)","Total Transport","8055","9638","78983","88621"],["Non Transport","I. Two wheelers","Scooters","86250","95122","628951","724073"],["Non Transport","I. Two wheelers","Mopeds","12559","14652","252297","266949"],["Non Transport","I. Two wheelers","Motor cycles","NA","NA","NA","NA"],["Non Transport","Total-I. Two wheelers","Total Two wheelers","98809","109774","881248","991022"],["Non Transport","II. Cars","Cars","4788","9207","34365","43572"],["Non Transport","III. Jeeps","Jeeps","153","175","7127","7302"],["Non Transport","IV. Omni buses","Omni buses","NA","NA","NA","NA"],["Non Transport","V. Tractors","Tractors","4440","5723","38598","44321"],["Non Transport","VI. Trailers","Trailers","4147","4943","33861","38804"],["Non Transport","VII. Other vehicles not covered","Other vehicles not covered","79","234","1869","2103"],["Non Transport","Total Non Transport (I to VII)","Total Non-Transport","112416","130056","997068","1127124"]]}