{"fields":[{"id":"a","label":"Type","type":"string"},{"id":"b","label":"Vehicles Category","type":"string"},{"id":"c","label":"Type of Vehicles","type":"string"},{"id":"d","label":"Newly registered-2004-05","type":"string"},{"id":"e","label":"Newly registered-2005-06","type":"string"},{"id":"f","label":"Total registered as on 31.3.2005","type":"string"},{"id":"g","label":"Total registered as on 31.3.2006","type":"string"}],"data":[["Transport","I. Multiaxled \/ Articulated Vehicles","Multiaxled \/ Articulated Vehicles","NA","NA","NA","NA"],["Transport","II. Trucks & Lorries","Trucks & Lorries","351","432","6314","6746"],["Transport","III. Light Motor Vehicles (Goods)","Four Wheelers","273","361","1479","1840"],["Transport","III. Light Motor Vehicles (Goods)","Three Wheelers","11","3","11","14"],["Transport","Total-III. Light Motor Vehicles (Goods)","Total Light Motor Vehicles (Goods)","284","364","1490","1854"],["Transport","IV. Buses","Stage carriages","58","69","1741","1810"],["Transport","IV. Buses","Contract carriages","3","0","75","75"],["Transport","IV. Buses","Private service vehicles","4","6","36","42"],["Transport","IV. Buses","Other buses","12","15","628","643"],["Transport","Total-IV. Buses","Total Buses","77","90","2480","2570"],["Transport","V. Taxis","Motor cabs","NA","NA","NA","NA"],["Transport","V. Taxis","Maxi cabs","0","0","11","11"],["Transport","V. Taxis","Other taxis","6","8","358","366"],["Transport","Total- V. Taxis","Total Taxis","6","8","369","377"],["Transport","VI. Light Motor Vehicles (Passengers)","Three seaters","108","91","2592","2683"],["Transport","VI. Light Motor Vehicles (Passengers)","Four to six seaters","1","NA","38","38"],["Transport","Total- VI. Light Motor Vehicles (Passengers)","Total Light Motor Vehicles (Passengers)","109","91","2630","2721"],["Transport","VII. Motor cycles on hire","Motor cycles on hire","NA","NA","NA","NA"],["Transport","Total Transport(I to VII)","Total Transport","827","985","13283","14268"],["Non Transport","I. Two wheelers","Scooters","2786","3325","52783","56108"],["Non Transport","I. Two wheelers","Mopeds","180","230","3401","3631"],["Non Transport","I. Two wheelers","Motor cycles","2258","2819","24373","27192"],["Non Transport","Total-I. Two wheelers","Total Two wheelers","5224","6374","80557","86931"],["Non Transport","II. Cars","Cars","1502","1701","9532","11233"],["Non Transport","III. Jeeps","Jeeps","397","299","8269","8568"],["Non Transport","IV. Omni buses","Omni buses","100","131","670","801"],["Non Transport","V. Tractors","Tractors","85","98","1348","1446"],["Non Transport","VI. Trailers","Trailers","7","25","587","612"],["Non Transport","VII. Other vehicles not covered","Other vehicles not covered","30","19","251","270"],["Non Transport","Total Non Transport (I to VII)","Total Non-Transport","7345","8647","101214","109861"]]}